sparrow/__init__.py
pysparrow-1.0.4.dist-info/LICENSE
pysparrow-1.0.4.dist-info/WHEEL
pysparrow-1.0.4.dist-info/METADATA
pysparrow-1.0.4.dist-info/RECORD
