Metadata-Version: 2.1
Name: pysparrow
Version: 1.0.4
Summary: An arrow interface for PySpark RDDs
Home-page: https://github.com/petereon/sparrow
License: MIT
Keywords: spark,arrow,>>,map,mappers
Author: Peter Vyboch
Author-email: pvyboch1@gmail.com
Requires-Python: >=3.6,<4.0
Classifier: License :: OSI Approved :: MIT License
Classifier: Natural Language :: English
Classifier: Programming Language :: Python :: 3
Classifier: Programming Language :: Python :: 3.10
Classifier: Programming Language :: Python :: 3.6
Classifier: Programming Language :: Python :: 3.7
Classifier: Programming Language :: Python :: 3.8
Classifier: Programming Language :: Python :: 3.9
Classifier: Topic :: Software Development :: Libraries
Classifier: Typing :: Typed
Requires-Dist: pyspark (>=3.2.1,<4.0.0)
Project-URL: Repository, https://github.com/petereon/sparrow
